bm25s/__init__.py
bm25s/hf.py
bm25s/scoring.py
bm25s/selection.py
bm25s/stopwords.py
bm25s/tokenization.py
bm25s/version.py
bm25s/numba/__init__.py
bm25s/numba/retrieve_utils.py
bm25s/numba/selection.py
bm25s/utils/__init__.py
bm25s/utils/beir.py
bm25s/utils/benchmark.py
bm25s/utils/corpus.py
bm25s/utils/json_functions.py
bm25s-0.2.14.dist-info/LICENSE
bm25s-0.2.14.dist-info/METADATA
bm25s-0.2.14.dist-info/WHEEL
bm25s-0.2.14.dist-info/top_level.txt
bm25s-0.2.14.dist-info/RECORD
