Metadata-Version: 2.1
Name: bm25s
Version: 0.2.14
Summary: An ultra-fast implementation of BM25 based on sparse matrices.
Home-page: https://github.com/xhluca/bm25s
Author: Xing Han Lù
Author-email: bm25s@googlegroups.com
Classifier: Programming Language :: Python :: 3
Classifier: License :: OSI Approved :: MIT License
Classifier: Operating System :: OS Independent
Requires-Python: >=3.8
Provides-Extra: core
Provides-Extra: stem
Provides-Extra: hf
Provides-Extra: dev
Provides-Extra: selection
Provides-Extra: evaluation
Provides-Extra: full
License-File: LICENSE
